{
  "openapi": "3.0.1",
  "info": {
    "title": "BlockSenseAPI",
    "version": "1.0"
  },
  "paths": {
    "/api/users/{uid}": {
      "get": {
        "tags": [
          "User"
        ],
        "parameters": [
          {
            "name": "uid",
            "in": "path",
            "required": true,
            "schema": {
              "type": "integer",
              "format": "int32"
            }
          }
        ],
        "responses": {
          "200": {
            "description": "OK"
          }
        }
      }
    },
    "/api/users/login": {
      "post": {
        "tags": [
          "User"
        ],
        "requestBody": {
          "content": {
            "application/json": {
              "schema": {
                "$ref": "#/components/schemas/LoginRequest"
              }
            },
            "text/json": {
              "schema": {
                "$ref": "#/components/schemas/LoginRequest"
              }
            },
            "application/*+json": {
              "schema": {
                "$ref": "#/components/schemas/LoginRequest"
              }
            }
          }
        },
        "responses": {
          "200": {
            "description": "OK"
          }
        }
      }
    },
    "/api/users/register": {
      "post": {
        "tags": [
          "User"
        ],
        "requestBody": {
          "content": {
            "application/json": {
              "schema": {
                "$ref": "#/components/schemas/RegisterRequest"
              }
            },
            "text/json": {
              "schema": {
                "$ref": "#/components/schemas/RegisterRequest"
              }
            },
            "application/*+json": {
              "schema": {
                "$ref": "#/components/schemas/RegisterRequest"
              }
            }
          }
        },
        "responses": {
          "200": {
            "description": "OK"
          }
        }
      }
    }
  },
  "components": {
    "schemas": {
      "LoginRequest": {
        "type": "object",
        "properties": {
          "login": {
            "type": "string",
            "nullable": true
          },
          "password": {
            "type": "string",
            "nullable": true
          },
          "identifiers": {
            "$ref": "#/components/schemas/SystemIdentifiers"
          }
        },
        "additionalProperties": false
      },
      "RegisterRequest": {
        "type": "object",
        "properties": {
          "username": {
            "type": "string",
            "nullable": true
          },
          "email": {
            "type": "string",
            "nullable": true
          },
          "password": {
            "type": "string",
            "nullable": true
          },
          "invitationCode": {
            "type": "string",
            "nullable": true
          }
        },
        "additionalProperties": false
      },
      "SystemIdentifiers": {
        "type": "object",
        "properties": {
          "deviceId": {
            "type": "string",
            "nullable": true
          },
          "ipAddress": {
            "type": "string",
            "nullable": true
          },
          "hardwareId": {
            "type": "string",
            "nullable": true
          },
          "macAddress": {
            "type": "string",
            "nullable": true
          }
        },
        "additionalProperties": false
      }
    }
  }
}